README.md
setup.py
centroiding/__init__.py
centroiding/centd.py
centroiding.egg-info/PKG-INFO
centroiding.egg-info/SOURCES.txt
centroiding.egg-info/dependency_links.txt
centroiding.egg-info/requires.txt
centroiding.egg-info/top_level.txt
centroiding/identify/__init__.py
centroiding/identify/centroiding.py
centroiding/identify/centroiding_multi.py
centroiding/identify/scripts/__init__.py
centroiding/identify/scripts/analyse_neighbours.py
centroiding/identify/scripts/detrend_centroid_external.py
centroiding/identify/scripts/get_scatter_color.py
centroiding/identify/scripts/inspect_blends.py
centroiding/identify/scripts/load_stacked_image.py
centroiding/identify/scripts/plotting.py
centroiding/identify/scripts/stacked_images.py
centroiding/test/__init__.py
centroiding/test/test_centroiding.py