Metadata-Version: 1.1
Name: centroiding
Version: 0.4.3
Summary: Centroiding analysis for transiting exoplanet candidate vetting
Home-page: https://github.com/MNGuenther/centroiding_pip
Author: Maximilian N. Guenther
Author-email: mg719@cam.ac.uk
License: UNKNOWN
Download-URL: https://github.com/MNGuenther/centroiding_pip
Platform: UNKNOWN
